factly/__init__.py
factly/ab_helper/__init__.py
factly/ab_helper/connections.py
factly/ab_helper/core/__init__.py
factly/ab_helper/core/configs.py
factly/ab_helper/destination.py
factly/ab_helper/models/__init__.py
factly/ab_helper/models/connection.py
factly/ab_helper/models/destination.py
factly/ab_helper/models/operation.py
factly/ab_helper/models/source.py
factly/ab_helper/models/workspace.py
factly/ab_helper/source.py
factly/ab_helper/sync.py
factly/ab_helper/utils.py
factly/ab_helper/workspace.py
ab_helper-0.1.1.dist-info/WHEEL
ab_helper-0.1.1.dist-info/METADATA
ab_helper-0.1.1.dist-info/RECORD
